haiblock/__init__.py
haiblock/base.py
haiblock-0.0.0.1.dist-info/licenses/LICENSE
haiblock-0.0.0.1.dist-info/METADATA
haiblock-0.0.0.1.dist-info/WHEEL
haiblock-0.0.0.1.dist-info/top_level.txt
haiblock-0.0.0.1.dist-info/RECORD
